hardware_communicator/__init__.py
hardware_communicator/abstract_communicator.py
hardware_communicator/usb_commmunicator.py
hardware_communicator/controller/__init__.py
hardware_communicator/controller/usb.py
hardware_communicator/message_interpreter/__init__.py
hardware_communicator/message_interpreter/basic_interpreter.py
hardware_communicator/message_interpreter/binary_interpreter.py
hardware_communicator-0.1.1607333155.dist-info/METADATA
hardware_communicator-0.1.1607333155.dist-info/WHEEL
hardware_communicator-0.1.1607333155.dist-info/top_level.txt
hardware_communicator-0.1.1607333155.dist-info/RECORD
