Metadata-Version: 2.1
Name: hardware-communicator
Version: 0.1.1607333155
Summary: HardwareCommunicator
Home-page: https://github.com/JulianKimmig/HardwareCommunicator
Author: Julian Kimmig
Author-email: julian-kimmig@gmx.net
License: UNKNOWN
Platform: UNKNOWN
Requires-Dist: json-dict
Requires-Dist: pyserial
Requires-Dist: data-recorder
Requires-Dist: Cython
